{"transcript":"ˈtɾɛw.ɾə","source":"treure","definitions":["To take out, to remove, to extract.","To pull out, to draw out.","To get, to obtain, to derive.","To take off (clothing, etc.).","To subtract (mathematics).","To bring out, to publish (a book, product, etc.).","To take a photo, to make a picture."],"examples":["Treure les escombraries.","Treure diners del banc.","Treure's la jaqueta.","Treure una conclusió.","Treure un llibre nou."],"lemma":"treure","lemmaPos":"verb","synonyms":["extreure","llevar","obtenir","sostreure","retirar"],"number":"singular"}